pyflycap2/__init__.py
pyflycap2/interface.pyd
pyflycap2/utils.py
pyflycap2-0.3.1.data/data/share/pyflycap2/flycapture2/bin/FlyCap2CameraControl_v140.dll
pyflycap2-0.3.1.data/data/share/pyflycap2/flycapture2/bin/FlyCapture2GUI_C_v140.dll
pyflycap2-0.3.1.data/data/share/pyflycap2/flycapture2/bin/FlyCapture2GUI_Managed_v140.dll
pyflycap2-0.3.1.data/data/share/pyflycap2/flycapture2/bin/FlyCapture2GUI_v140.dll
pyflycap2-0.3.1.data/data/share/pyflycap2/flycapture2/bin/FlyCapture2Managed_v140.dll
pyflycap2-0.3.1.data/data/share/pyflycap2/flycapture2/bin/FlyCapture2Video_C_v140.dll
pyflycap2-0.3.1.data/data/share/pyflycap2/flycapture2/bin/FlyCapture2Video_Managed_v140.dll
pyflycap2-0.3.1.data/data/share/pyflycap2/flycapture2/bin/FlyCapture2Video_v140.dll
pyflycap2-0.3.1.data/data/share/pyflycap2/flycapture2/bin/FlyCapture2_C_v140.dll
pyflycap2-0.3.1.data/data/share/pyflycap2/flycapture2/bin/FlyCapture2_v140.dll
pyflycap2-0.3.1.data/data/share/pyflycap2/flycapture2/bin/libiomp5md.dll
pyflycap2-0.3.1.data/data/share/pyflycap2/flycapture2/bin/msvcp140.dll
pyflycap2-0.3.1.dist-info/LICENSE
pyflycap2-0.3.1.dist-info/METADATA
pyflycap2-0.3.1.dist-info/WHEEL
pyflycap2-0.3.1.dist-info/top_level.txt
pyflycap2-0.3.1.dist-info/RECORD
