Metadata-Version: 2.1
Name: pyflycap2
Version: 0.3.1
Summary: Cython bindings for Point Gray Fly Capture 2.
Home-page: https://matham.github.io/pyflycap2/
Author: Matthew Einhorn
License: MIT
Platform: UNKNOWN
Classifier: License :: OSI Approved :: MIT License
Classifier: Topic :: Multimedia :: Graphics :: Capture :: Digital Camera
Classifier: Topic :: Multimedia :: Graphics :: Capture
Classifier: Programming Language :: Python :: 3.5
Classifier: Programming Language :: Python :: 3.6
Classifier: Programming Language :: Python :: 3.7
Classifier: Operating System :: Microsoft :: Windows
Classifier: Operating System :: POSIX :: Linux
Classifier: Intended Audience :: Developers
License-File: LICENSE
